{
  "generated_at": "2026-06-10T14:01:29.677881",
  "elapsed_seconds": 55.3,
  "market_regime": {
    "regime": "bull",
    "spy_price": 735.23,
    "spy_50ma": 719.52,
    "spy_200ma": 683.11,
    "spy_3m_return": 10.7,
    "rs_threshold": 70,
    "note": "SPY: golden alignment \u2014 normal thresholds"
  },
  "universe_size": 518,
  "rs_qualifying": 159,
  "quality_pass": 154,
  "tech_gate_pass": 50,
  "final_count": 50,
  "sector_leaders": [
    "energy",
    "technology",
    "basic_materials",
    "industrials",
    "financials",
    "real_estate"
  ],
  "rejection_stats": {
    "rs_rank": 359,
    "quality": 5,
    "technical": 35
  },
  "candidates": [
    {
      "symbol": "HPE",
      "rs_rank": 98,
      "rs_score": 52.4,
      "thesis_score": 49.0,
      "thesis_grade": "C",
      "setup_reason": "highly extended 97% \u2014 late entry risk",
      "effective_score": 82.3,
      "sector": "technology",
      "sector_leader": true,
      "trend": "strong_up",
      "price": 46.99,
      "sma50": 33.01,
      "sma200": 25.37,
      "ret_1m": 55.6,
      "ret_3m": 119.2,
      "ret_6m": 92.1,
      "source": "screener",
      "priority": 0
    },
    {
      "symbol": "DELL",
      "rs_rank": 98,
      "rs_score": 71.1,
      "thesis_score": 42.0,
      "thesis_grade": "C",
      "setup_reason": "highly extended 140% \u2014 late entry risk",
      "effective_score": 79.4,
      "sector": "technology",
      "sector_leader": true,
      "trend": "strong_up",
      "price": 392.02,
      "sma50": 254.92,
      "sma200": 164.69,
      "ret_1m": 64.1,
      "ret_3m": 162.3,
      "ret_6m": 185.7,
      "source": "screener",
      "priority": 0
    },
    {
      "symbol": "INTC",
      "rs_rank": 99,
      "rs_score": 72.5,
      "thesis_score": 38.0,
      "thesis_grade": "D",
      "setup_reason": "highly extended 144% \u2014 late entry risk \u00b7 room to run in BB",
      "effective_score": 78.3,
      "sector": "technology",
      "sector_leader": true,
      "trend": "strong_up",
      "price": 107.53,
      "sma50": 92.71,
      "sma200": 52.54,
      "ret_1m": -10.8,
      "ret_3m": 137.6,
      "ret_6m": 165.5,
      "source": "screener",
      "priority": 0
    },
    {
      "symbol": "MU",
      "rs_rank": 99,
      "rs_score": 83.0,
      "thesis_score": 38.0,
      "thesis_grade": "D",
      "setup_reason": "highly extended 171% \u2014 late entry risk \u00b7 room to run in BB",
      "effective_score": 78.3,
      "sector": "technology",
      "sector_leader": true,
      "trend": "strong_up",
      "price": 914.14,
      "sma50": 652.66,
      "sma200": 372.96,
      "ret_1m": 19.2,
      "ret_3m": 125.6,
      "ret_6m": 262.4,
      "source": "screener",
      "priority": 0
    },
    {
      "symbol": "STX",
      "rs_rank": 99,
      "rs_score": 74.8,
      "thesis_score": 38.0,
      "thesis_grade": "D",
      "setup_reason": "highly extended 111% \u2014 late entry risk \u00b7 room to run in BB",
      "effective_score": 78.3,
      "sector": "technology",
      "sector_leader": true,
      "trend": "strong_up",
      "price": 826.31,
      "sma50": 694.53,
      "sma200": 396.28,
      "ret_1m": 2.2,
      "ret_3m": 121.3,
      "ret_6m": 193.4,
      "source": "screener",
      "priority": 0
    },
    {
      "symbol": "WDC",
      "rs_rank": 99,
      "rs_score": 76.8,
      "thesis_score": 38.0,
      "thesis_grade": "D",
      "setup_reason": "highly extended 84% \u2014 late entry risk \u00b7 room to run in BB",
      "effective_score": 78.3,
      "sector": "technology",
      "sector_leader": true,
      "trend": "strong_up",
      "price": 497.66,
      "sma50": 438.69,
      "sma200": 248.98,
      "ret_1m": 1.9,
      "ret_3m": 90.6,
      "ret_6m": 193.8,
      "source": "screener",
      "priority": 0
    },
    {
      "symbol": "NTAP",
      "rs_rank": 95,
      "rs_score": 28.0,
      "thesis_score": 43.0,
      "thesis_grade": "C",
      "setup_reason": "highly extended 72% \u2014 late entry risk",
      "effective_score": 77.9,
      "sector": "technology",
      "sector_leader": true,
      "trend": "strong_up",
      "price": 164.14,
      "sma50": 123.22,
      "sma200": 112.65,
      "ret_1m": 41.2,
      "ret_3m": 70.2,
      "ret_6m": 41.3,
      "source": "screener",
      "priority": 0
    },
    {
      "symbol": "AMD",
      "rs_rank": 98,
      "rs_score": 66.0,
      "thesis_score": 38.0,
      "thesis_grade": "D",
      "setup_reason": "highly extended 130% \u2014 late entry risk \u00b7 room to run in BB",
      "effective_score": 77.7,
      "sector": "technology",
      "sector_leader": true,
      "trend": "strong_up",
      "price": 467.01,
      "sma50": 375.34,
      "sma200": 250.65,
      "ret_1m": 4.2,
      "ret_3m": 136.2,
      "ret_6m": 110.7,
      "source": "screener",
      "priority": 0
    },
    {
      "symbol": "ARM",
      "rs_rank": 98,
      "rs_score": 69.0,
      "thesis_score": 38.0,
      "thesis_grade": "D",
      "setup_reason": "highly extended 125% \u2014 late entry risk \u00b7 room to run in BB",
      "effective_score": 77.7,
      "sector": "technology",
      "sector_leader": true,
      "trend": "strong_up",
      "price": 323.52,
      "sma50": 234.99,
      "sma200": 160.12,
      "ret_1m": 55.6,
      "ret_3m": 181.0,
      "ret_6m": 127.9,
      "source": "screener",
      "priority": 0
    },
    {
      "symbol": "MRVL",
      "rs_rank": 99,
      "rs_score": 85.1,
      "thesis_score": 36.0,
      "thesis_grade": "D",
      "setup_reason": "highly extended 164% \u2014 late entry risk",
      "effective_score": 77.5,
      "sector": "technology",
      "sector_leader": true,
      "trend": "strong_up",
      "price": 261.39,
      "sma50": 176.07,
      "sma200": 106.43,
      "ret_1m": 58.9,
      "ret_3m": 198.3,
      "ret_6m": 194.4,
      "source": "screener",
      "priority": 0
    },
    {
      "symbol": "SNDK",
      "rs_rank": 99,
      "rs_score": 159.6,
      "thesis_score": 36.0,
      "thesis_grade": "D",
      "setup_reason": "highly extended 164% \u2014 late entry risk",
      "effective_score": 77.5,
      "sector": "technology",
      "sector_leader": true,
      "trend": "strong_up",
      "price": 1675.81,
      "sma50": 1243.34,
      "sma200": 554.38,
      "ret_1m": 15.4,
      "ret_3m": 170.8,
      "ret_6m": 663.6,
      "source": "screener",
      "priority": 0
    },
    {
      "symbol": "HAL",
      "rs_rank": 87,
      "rs_score": 17.1,
      "thesis_score": 54.0,
      "thesis_grade": "C",
      "setup_reason": "fresh setup (10% from base) \u00b7 room to run in BB",
      "effective_score": 77.5,
      "sector": "energy",
      "sector_leader": true,
      "trend": "strong_up",
      "price": 40.05,
      "sma50": 39.75,
      "sma200": 31.47,
      "ret_1m": -3.5,
      "ret_3m": 15.4,
      "ret_6m": 41.4,
      "source": "screener",
      "priority": 0
    },
    {
      "symbol": "ON",
      "rs_rank": 97,
      "rs_score": 40.1,
      "thesis_score": 38.0,
      "thesis_grade": "D",
      "setup_reason": "highly extended 82% \u2014 late entry risk \u00b7 room to run in BB",
      "effective_score": 77.1,
      "sector": "technology",
      "sector_leader": true,
      "trend": "strong_up",
      "price": 112.97,
      "sma50": 99.06,
      "sma200": 66.48,
      "ret_1m": 8.5,
      "ret_3m": 95.8,
      "ret_6m": 104.5,
      "source": "screener",
      "priority": 0
    },
    {
      "symbol": "TER",
      "rs_rank": 97,
      "rs_score": 40.2,
      "thesis_score": 38.0,
      "thesis_grade": "D",
      "setup_reason": "extended 23% from base \u00b7 room to run in BB",
      "effective_score": 77.1,
      "sector": "technology",
      "sector_leader": true,
      "trend": "strong_up",
      "price": 365.27,
      "sma50": 361.27,
      "sma200": 244.51,
      "ret_1m": 1.9,
      "ret_3m": 27.5,
      "ret_6m": 82.8,
      "source": "screener",
      "priority": 0
    },
    {
      "symbol": "DDOG",
      "rs_rank": 96,
      "rs_score": 35.0,
      "thesis_score": 38.0,
      "thesis_grade": "D",
      "setup_reason": "highly extended 121% \u2014 late entry risk \u00b7 room to run in BB",
      "effective_score": 76.4,
      "sector": "technology",
      "sector_leader": true,
      "trend": "strong_up",
      "price": 232.58,
      "sma50": 172.73,
      "sma200": 148.57,
      "ret_1m": 16.3,
      "ret_3m": 82.9,
      "ret_6m": 52.4,
      "source": "screener",
      "priority": 0
    },
    {
      "symbol": "LRCX",
      "rs_rank": 97,
      "rs_score": 44.4,
      "thesis_score": 36.0,
      "thesis_grade": "D",
      "setup_reason": "highly extended 58% \u2014 late entry risk",
      "effective_score": 76.2,
      "sector": "technology",
      "sector_leader": true,
      "trend": "strong_up",
      "price": 337.68,
      "sma50": 280.37,
      "sma200": 201.71,
      "ret_1m": 16.7,
      "ret_3m": 61.2,
      "ret_6m": 103.9,
      "source": "screener",
      "priority": 0
    },
    {
      "symbol": "HUM",
      "rs_rank": 97,
      "rs_score": 44.0,
      "thesis_score": 44.0,
      "thesis_grade": "C",
      "setup_reason": "highly extended 108% \u2014 late entry risk \u00b7 BB overextended (%B=0.97)",
      "effective_score": 75.8,
      "sector": "healthcare",
      "sector_leader": false,
      "trend": "strong_up",
      "price": 361.49,
      "sma50": 259.5,
      "sma200": 245.43,
      "ret_1m": 22.4,
      "ret_3m": 122.0,
      "ret_6m": 45.6,
      "source": "screener",
      "priority": 1
    },
    {
      "symbol": "CASY",
      "rs_rank": 90,
      "rs_score": 18.6,
      "thesis_score": 54.0,
      "thesis_grade": "C",
      "setup_reason": "modest extension (20% from base)",
      "effective_score": 75.6,
      "sector": "consumer_cyclical",
      "sector_leader": false,
      "trend": "strong_up",
      "price": 871.3,
      "sma50": 795.59,
      "sma200": 638.41,
      "ret_1m": 0.5,
      "ret_3m": 29.4,
      "ret_6m": 54.9,
      "source": "screener",
      "priority": 1
    },
    {
      "symbol": "ADI",
      "rs_rank": 90,
      "rs_score": 18.7,
      "thesis_score": 44.0,
      "thesis_grade": "C",
      "setup_reason": "extended 27% from base \u00b7 room to run in BB",
      "effective_score": 75.2,
      "sector": "technology",
      "sector_leader": true,
      "trend": "strong_up",
      "price": 403.3,
      "sma50": 388.83,
      "sma200": 303.87,
      "ret_1m": -3.6,
      "ret_3m": 31.6,
      "ret_6m": 46.9,
      "source": "screener",
      "priority": 0
    },
    {
      "symbol": "CSCO",
      "rs_rank": 94,
      "rs_score": 25.7,
      "thesis_score": 38.0,
      "thesis_grade": "D",
      "setup_reason": "highly extended 54% \u2014 late entry risk \u00b7 room to run in BB",
      "effective_score": 75.2,
      "sector": "technology",
      "sector_leader": true,
      "trend": "strong_up",
      "price": 118.88,
      "sma50": 100.22,
      "sma200": 80.56,
      "ret_1m": 19.7,
      "ret_3m": 53.7,
      "ret_6m": 51.1,
      "source": "screener",
      "priority": 0
    },
    {
      "symbol": "MPWR",
      "rs_rank": 94,
      "rs_score": 26.6,
      "thesis_score": 38.0,
      "thesis_grade": "D",
      "setup_reason": "highly extended 40% \u2014 late entry risk \u00b7 room to run in BB",
      "effective_score": 75.2,
      "sector": "technology",
      "sector_leader": true,
      "trend": "strong_up",
      "price": 1525.52,
      "sma50": 1501.19,
      "sma200": 1121.69,
      "ret_1m": -4.6,
      "ret_3m": 47.8,
      "ret_6m": 59.0,
      "source": "screener",
      "priority": 0
    },
    {
      "symbol": "NUE",
      "rs_rank": 95,
      "rs_score": 28.1,
      "thesis_score": 36.0,
      "thesis_grade": "D",
      "setup_reason": "highly extended 51% \u2014 late entry risk",
      "effective_score": 75.0,
      "sector": "basic_materials",
      "sector_leader": true,
      "trend": "strong_up",
      "price": 255.27,
      "sma50": 219.98,
      "sma200": 173.14,
      "ret_1m": 11.1,
      "ret_3m": 54.6,
      "ret_6m": 62.5,
      "source": "screener",
      "priority": 0
    },
    {
      "symbol": "CHRW",
      "rs_rank": 88,
      "rs_score": 17.4,
      "thesis_score": 55.0,
      "thesis_grade": "B",
      "setup_reason": "modest extension (19% from base)",
      "effective_score": 74.8,
      "sector": "industrials",
      "sector_leader": false,
      "trend": "strong_up",
      "price": 189.02,
      "sma50": 174.89,
      "sma200": 160.75,
      "ret_1m": 13.4,
      "ret_3m": 10.4,
      "ret_6m": 24.8,
      "source": "screener",
      "priority": 1
    },
    {
      "symbol": "COHR",
      "rs_rank": 97,
      "rs_score": 47.9,
      "thesis_score": 32.0,
      "thesis_grade": "D",
      "setup_reason": "highly extended 53% \u2014 late entry risk \u00b7 room to run in BB",
      "effective_score": 74.5,
      "sector": "technology",
      "sector_leader": true,
      "trend": "strong_up",
      "price": 364.25,
      "sma50": 341.84,
      "sma200": 215.11,
      "ret_1m": -2.6,
      "ret_3m": 51.0,
      "ret_6m": 89.0,
      "source": "screener",
      "priority": 0
    },
    {
      "symbol": "JBL",
      "rs_rank": 94,
      "rs_score": 25.8,
      "thesis_score": 36.0,
      "thesis_grade": "D",
      "setup_reason": "highly extended 38% \u2014 late entry risk",
      "effective_score": 74.3,
      "sector": "technology",
      "sector_leader": true,
      "trend": "strong_up",
      "price": 367.06,
      "sma50": 336.17,
      "sma200": 255.54,
      "ret_1m": 4.7,
      "ret_3m": 45.6,
      "ret_6m": 61.0,
      "source": "screener",
      "priority": 0
    },
    {
      "symbol": "FDX",
      "rs_rank": 85,
      "rs_score": 15.8,
      "thesis_score": 58.0,
      "thesis_grade": "B",
      "setup_reason": "modest extension (13% from base) \u00b7 room to run in BB",
      "effective_score": 74.2,
      "sector": "industrials",
      "sector_leader": false,
      "trend": "strong_up",
      "price": 323.7,
      "sma50": 310.57,
      "sma200": 252.26,
      "ret_1m": 6.7,
      "ret_3m": 13.8,
      "ret_6m": 47.4,
      "source": "screener",
      "priority": 1
    },
    {
      "symbol": "CAT",
      "rs_rank": 94,
      "rs_score": 26.2,
      "thesis_score": 44.0,
      "thesis_grade": "C",
      "setup_reason": "extended 25% from base \u00b7 room to run in BB",
      "effective_score": 74.0,
      "sector": "industrials",
      "sector_leader": false,
      "trend": "strong_up",
      "price": 887.05,
      "sma50": 848.06,
      "sma200": 653.36,
      "ret_1m": -2.8,
      "ret_3m": 26.8,
      "ret_6m": 49.9,
      "source": "screener",
      "priority": 1
    },
    {
      "symbol": "STLD",
      "rs_rank": 96,
      "rs_score": 28.5,
      "thesis_score": 31.0,
      "thesis_grade": "D",
      "setup_reason": "highly extended 54% \u2014 late entry risk",
      "effective_score": 73.5,
      "sector": "basic_materials",
      "sector_leader": true,
      "trend": "strong_up",
      "price": 272.02,
      "sma50": 227.61,
      "sma200": 179.22,
      "ret_1m": 16.8,
      "ret_3m": 55.8,
      "ret_6m": 65.4,
      "source": "screener",
      "priority": 0
    },
    {
      "symbol": "NXPI",
      "rs_rank": 91,
      "rs_score": 19.4,
      "thesis_score": 38.0,
      "thesis_grade": "D",
      "setup_reason": "highly extended 50% \u2014 late entry risk \u00b7 room to run in BB",
      "effective_score": 73.3,
      "sector": "technology",
      "sector_leader": true,
      "trend": "strong_up",
      "price": 292.45,
      "sma50": 268.0,
      "sma200": 230.45,
      "ret_1m": -0.6,
      "ret_3m": 53.7,
      "ret_6m": 29.5,
      "source": "screener",
      "priority": 0
    },
    {
      "symbol": "TXN",
      "rs_rank": 91,
      "rs_score": 20.1,
      "thesis_score": 38.0,
      "thesis_grade": "D",
      "setup_reason": "highly extended 49% \u2014 late entry risk \u00b7 room to run in BB",
      "effective_score": 73.3,
      "sector": "technology",
      "sector_leader": true,
      "trend": "strong_up",
      "price": 287.36,
      "sma50": 268.18,
      "sma200": 205.37,
      "ret_1m": -2.6,
      "ret_3m": 52.0,
      "ret_6m": 61.9,
      "source": "screener",
      "priority": 0
    },
    {
      "symbol": "VLO",
      "rs_rank": 87,
      "rs_score": 17.1,
      "thesis_score": 44.0,
      "thesis_grade": "C",
      "setup_reason": "modest extension (15% from base)",
      "effective_score": 73.3,
      "sector": "energy",
      "sector_leader": true,
      "trend": "strong_up",
      "price": 255.75,
      "sma50": 244.32,
      "sma200": 196.25,
      "ret_1m": 4.0,
      "ret_3m": 9.0,
      "ret_6m": 47.5,
      "source": "screener",
      "priority": 0
    },
    {
      "symbol": "SLB",
      "rs_rank": 85,
      "rs_score": 16.0,
      "thesis_score": 46.0,
      "thesis_grade": "C",
      "setup_reason": "modest extension (14% from base) \u00b7 room to run in BB",
      "effective_score": 72.9,
      "sector": "energy",
      "sector_leader": true,
      "trend": "strong_up",
      "price": 56.23,
      "sma50": 54.31,
      "sma200": 43.92,
      "ret_1m": 1.6,
      "ret_3m": 26.9,
      "ret_6m": 48.5,
      "source": "screener",
      "priority": 0
    },
    {
      "symbol": "CMI",
      "rs_rank": 92,
      "rs_score": 20.5,
      "thesis_score": 44.0,
      "thesis_grade": "C",
      "setup_reason": "extended 23% from base \u00b7 room to run in BB",
      "effective_score": 72.8,
      "sector": "industrials",
      "sector_leader": false,
      "trend": "strong_up",
      "price": 660.46,
      "sma50": 645.55,
      "sma200": 531.32,
      "ret_1m": -6.0,
      "ret_3m": 23.0,
      "ret_6m": 32.9,
      "source": "screener",
      "priority": 1
    },
    {
      "symbol": "AKAM",
      "rs_rank": 90,
      "rs_score": 18.5,
      "thesis_score": 38.0,
      "thesis_grade": "D",
      "setup_reason": "highly extended 54% \u2014 late entry risk \u00b7 room to run in BB",
      "effective_score": 72.7,
      "sector": "technology",
      "sector_leader": true,
      "trend": "strong_up",
      "price": 136.84,
      "sma50": 124.75,
      "sma200": 97.52,
      "ret_1m": -8.5,
      "ret_3m": 29.7,
      "ret_6m": 59.7,
      "source": "screener",
      "priority": 0
    },
    {
      "symbol": "ROST",
      "rs_rank": 80,
      "rs_score": 13.2,
      "thesis_score": 61.0,
      "thesis_grade": "B",
      "setup_reason": "fresh setup (10% from base) \u00b7 tight base",
      "effective_score": 72.4,
      "sector": "consumer_cyclical",
      "sector_leader": false,
      "trend": "strong_up",
      "price": 231.62,
      "sma50": 223.69,
      "sma200": 187.7,
      "ret_1m": 6.6,
      "ret_3m": 10.8,
      "ret_6m": 31.4,
      "source": "screener",
      "priority": 1
    },
    {
      "symbol": "BG",
      "rs_rank": 80,
      "rs_score": 12.4,
      "thesis_score": 61.0,
      "thesis_grade": "B",
      "setup_reason": "fresh setup (7% from base) \u00b7 tight base",
      "effective_score": 72.4,
      "sector": "consumer_defensive",
      "sector_leader": false,
      "trend": "strong_up",
      "price": 126.79,
      "sma50": 124.54,
      "sma200": 105.11,
      "ret_1m": 1.1,
      "ret_3m": 1.4,
      "ret_6m": 40.3,
      "source": "screener",
      "priority": 1
    },
    {
      "symbol": "CNC",
      "rs_rank": 95,
      "rs_score": 28.4,
      "thesis_score": 38.0,
      "thesis_grade": "D",
      "setup_reason": "highly extended 97% \u2014 late entry risk \u00b7 BB overextended (%B=0.92)",
      "effective_score": 72.2,
      "sector": "healthcare",
      "sector_leader": false,
      "trend": "strong_up",
      "price": 64.49,
      "sma50": 50.44,
      "sma200": 41.03,
      "ret_1m": 8.7,
      "ret_3m": 86.5,
      "ret_6m": 69.4,
      "source": "screener",
      "priority": 1
    },
    {
      "symbol": "GNRC",
      "rs_rank": 91,
      "rs_score": 19.2,
      "thesis_score": 44.0,
      "thesis_grade": "C",
      "setup_reason": "extended 28% from base \u00b7 room to run in BB",
      "effective_score": 72.2,
      "sector": "industrials",
      "sector_leader": false,
      "trend": "strong_up",
      "price": 245.4,
      "sma50": 242.46,
      "sma200": 193.25,
      "ret_1m": -9.0,
      "ret_3m": 20.2,
      "ret_6m": 53.3,
      "source": "screener",
      "priority": 1
    },
    {
      "symbol": "AMAT",
      "rs_rank": 97,
      "rs_score": 38.7,
      "thesis_score": 26.0,
      "thesis_grade": "D",
      "setup_reason": "highly extended 52% \u2014 late entry risk \u00b7 BB overextended (%B=1.00)",
      "effective_score": 72.0,
      "sector": "technology",
      "sector_leader": true,
      "trend": "strong_up",
      "price": 520.51,
      "sma50": 418.84,
      "sma200": 304.74,
      "ret_1m": 20.9,
      "ret_3m": 54.5,
      "ret_6m": 95.3,
      "source": "screener",
      "priority": 0
    },
    {
      "symbol": "QCOM",
      "rs_rank": 89,
      "rs_score": 18.3,
      "thesis_score": 38.0,
      "thesis_grade": "D",
      "setup_reason": "highly extended 61% \u2014 late entry risk \u00b7 room to run in BB",
      "effective_score": 72.0,
      "sector": "technology",
      "sector_leader": true,
      "trend": "strong_up",
      "price": 199.17,
      "sma50": 180.43,
      "sma200": 163.58,
      "ret_1m": -4.9,
      "ret_3m": 52.4,
      "ret_6m": 14.3,
      "source": "screener",
      "priority": 0
    },
    {
      "symbol": "DAL",
      "rs_rank": 88,
      "rs_score": 18.1,
      "thesis_score": 48.0,
      "thesis_grade": "C",
      "setup_reason": "extended 21% from base",
      "effective_score": 72.0,
      "sector": "industrials",
      "sector_leader": false,
      "trend": "strong_up",
      "price": 79.42,
      "sma50": 72.22,
      "sma200": 65.75,
      "ret_1m": 12.6,
      "ret_3m": 37.4,
      "ret_6m": 18.4,
      "source": "screener",
      "priority": 1
    },
    {
      "symbol": "HST",
      "rs_rank": 87,
      "rs_score": 16.8,
      "thesis_score": 49.0,
      "thesis_grade": "C",
      "setup_reason": "extended 28% from base",
      "effective_score": 71.8,
      "sector": "real_estate",
      "sector_leader": false,
      "trend": "strong_up",
      "price": 24.39,
      "sma50": 21.64,
      "sma200": 18.6,
      "ret_1m": 12.1,
      "ret_3m": 31.8,
      "ret_6m": 44.0,
      "source": "screener",
      "priority": 1
    },
    {
      "symbol": "FTNT",
      "rs_rank": 93,
      "rs_score": 23.1,
      "thesis_score": 30.0,
      "thesis_grade": "D",
      "setup_reason": "highly extended 82% \u2014 late entry risk",
      "effective_score": 71.2,
      "sector": "technology",
      "sector_leader": true,
      "trend": "strong_up",
      "price": 139.82,
      "sma50": 106.43,
      "sma200": 87.86,
      "ret_1m": 22.8,
      "ret_3m": 65.7,
      "ret_6m": 67.5,
      "source": "screener",
      "priority": 0
    },
    {
      "symbol": "TPR",
      "rs_rank": 82,
      "rs_score": 13.9,
      "thesis_score": 55.0,
      "thesis_grade": "B",
      "setup_reason": "modest extension (12% from base)",
      "effective_score": 71.2,
      "sector": "consumer_cyclical",
      "sector_leader": false,
      "trend": "strong_up",
      "price": 144.68,
      "sma50": 141.86,
      "sma200": 127.9,
      "ret_1m": 10.1,
      "ret_3m": 1.7,
      "ret_6m": 23.1,
      "source": "screener",
      "priority": 1
    },
    {
      "symbol": "KLAC",
      "rs_rank": 96,
      "rs_score": 35.1,
      "thesis_score": 25.0,
      "thesis_grade": "D",
      "setup_reason": "highly extended 53% \u2014 late entry risk \u00b7 BB overextended (%B=1.04)",
      "effective_score": 71.0,
      "sector": "technology",
      "sector_leader": true,
      "trend": "strong_up",
      "price": 2250.33,
      "sma50": 1825.94,
      "sma200": 1393.58,
      "ret_1m": 24.4,
      "ret_3m": 59.9,
      "ret_6m": 84.1,
      "source": "screener",
      "priority": 0
    },
    {
      "symbol": "PWR",
      "rs_rank": 89,
      "rs_score": 18.4,
      "thesis_score": 44.0,
      "thesis_grade": "C",
      "setup_reason": "extended 23% from base \u00b7 room to run in BB",
      "effective_score": 71.0,
      "sector": "industrials",
      "sector_leader": false,
      "trend": "strong_up",
      "price": 676.4,
      "sma50": 674.32,
      "sma200": 513.65,
      "ret_1m": -11.7,
      "ret_3m": 19.3,
      "ret_6m": 47.8,
      "source": "screener",
      "priority": 1
    },
    {
      "symbol": "CRWD",
      "rs_rank": 91,
      "rs_score": 19.0,
      "thesis_score": 32.0,
      "thesis_grade": "D",
      "setup_reason": "highly extended 73% \u2014 late entry risk \u00b7 room to run in BB",
      "effective_score": 70.8,
      "sector": "technology",
      "sector_leader": true,
      "trend": "strong_up",
      "price": 656.19,
      "sma50": 532.06,
      "sma200": 481.57,
      "ret_1m": 20.1,
      "ret_3m": 48.6,
      "ret_6m": 26.7,
      "source": "screener",
      "priority": 0
    },
    {
      "symbol": "GOOG",
      "rs_rank": 92,
      "rs_score": 20.3,
      "thesis_score": 39.0,
      "thesis_grade": "D",
      "setup_reason": "extended 27% from base \u00b7 room to run in BB",
      "effective_score": 70.8,
      "sector": "communication_services",
      "sector_leader": false,
      "trend": "strong_up",
      "price": 363.62,
      "sma50": 356.83,
      "sma200": 305.69,
      "ret_1m": -5.2,
      "ret_3m": 20.0,
      "ret_6m": 14.6,
      "source": "screener",
      "priority": 1
    },
    {
      "symbol": "GOOGL",
      "rs_rank": 92,
      "rs_score": 20.7,
      "thesis_score": 39.0,
      "thesis_grade": "D",
      "setup_reason": "extended 27% from base \u00b7 room to run in BB",
      "effective_score": 70.8,
      "sector": "communication_services",
      "sector_leader": false,
      "trend": "strong_up",
      "price": 365.83,
      "sma50": 359.59,
      "sma200": 306.1,
      "ret_1m": -5.5,
      "ret_3m": 20.6,
      "ret_6m": 15.5,
      "source": "screener",
      "priority": 1
    },
    {
      "symbol": "PANW",
      "rs_rank": 91,
      "rs_score": 19.8,
      "thesis_score": 32.0,
      "thesis_grade": "D",
      "setup_reason": "highly extended 69% \u2014 late entry risk \u00b7 room to run in BB",
      "effective_score": 70.8,
      "sector": "technology",
      "sector_leader": true,
      "trend": "strong_up",
      "price": 263.4,
      "sma50": 210.51,
      "sma200": 193.31,
      "ret_1m": 22.2,
      "ret_3m": 56.7,
      "ret_6m": 35.1,
      "source": "screener",
      "priority": 0
    }
  ]
}